env_wrangler/__init__.py
env_wrangler/cli.py
env_wrangler/constants.py
env_wrangler/core.py
env_wrangler/settings.py
env_wrangler/utils.py
env_wrangler/data/env-wrangler.toml
env_wrangler-0.1.6.dist-info/licenses/AUTHORS.md
env_wrangler-0.1.6.dist-info/licenses/LICENSE
env_wrangler-0.1.6.dist-info/METADATA
env_wrangler-0.1.6.dist-info/WHEEL
env_wrangler-0.1.6.dist-info/entry_points.txt
env_wrangler-0.1.6.dist-info/top_level.txt
env_wrangler-0.1.6.dist-info/RECORD
