Metadata-Version: 2.4
Name: env-wrangler
Version: 0.1.6
Summary: Extract secrets from .env files into their own file (either `.secrets` or `secrets.json`). Also provides `mask` and `unmask` options. The resulting secrets file can be leveraged to get your secrets into a 3rd party secrets manager like AWS Secrets Manager or something else.
Author-email: Tim Santor <tsantor@xstudios.com>
Project-URL: Repository, https://github.com/tsantor/env-wrangler.git
Project-URL: Issues, https://github.com/tsantor/env-wrangler/issues
Project-URL: Changelog, https://github.com/tsantor/env-wrangler/blob/master/HISTORY.md
Classifier: Development Status :: 5 - Production/Stable
Classifier: Environment :: Console
Classifier: Intended Audience :: Developers
Classifier: Natural Language :: English
Classifier: Programming Language :: Python :: 3.8
Classifier: Programming Language :: Python :: 3.9
Classifier: Programming Language :: Python :: 3.10
Classifier: Programming Language :: Python :: 3.11
Classifier: Programming Language :: Python :: 3.12
Requires-Python: >=3.8
License-File: LICENSE
License-File: AUTHORS.md
Requires-Dist: click>=8.1.8
Requires-Dist: python-dotenv>=1.0.1
Requires-Dist: setuptools>=75.3.2
Requires-Dist: toml>=0.10.2
Provides-Extra: dev
Dynamic: license-file
